<?xml version='1.0' encoding='UTF-8'?>
<!-- Published by JAX-WS RI at http://jax-ws.dev.java.net. RI's version is JAX-WS RI 2.2.8 svn-revision#13980. -->
<!-- Generated by JAX-WS RI at http://jax-ws.dev.java.net. RI's version is JAX-WS RI 2.2.8 svn-revision#13980. -->
<definitions xmlns:wsu="http://docs.oasis-open.org/wss/2004/01/oasis-200401-wss-wssecurity-utility-1.0.xsd" xmlns:wsp="http://www.w3.org/ns/ws-policy" xmlns:wsp1_2="http://schemas.xmlsoap.org/ws/2004/09/policy" xmlns:wsam="http://www.w3.org/2007/05/addressing/metadata" xmlns:soap="http://schemas.xmlsoap.org/wsdl/soap/" xmlns:tns="http://soapservermaven.mycompany.com/" xmlns:xsd="http://www.w3.org/2001/XMLSchema" xmlns="http://schemas.xmlsoap.org/wsdl/" targetNamespace="http://soapservermaven.mycompany.com/" name="mySOAPServer">
    <types>
        <xsd:schema>
            <xsd:import namespace="http://soapservermaven.mycompany.com/" schemaLocation="http://localhost:1234/recipielist?xsd=1"/>
        </xsd:schema>
    </types>
    <message name="testServerreturn">
        <part name="parameters" element="tns:testServerreturn"/>
    </message>
    <message name="testServerreturnResponse">
        <part name="parameters" element="tns:testServerreturnResponse"/>
    </message>
    <message name="getAllItems">
        <part name="parameters" element="tns:getAllItems"/>
    </message>
    <message name="getAllItemsResponse">
        <part name="parameters" element="tns:getAllItemsResponse"/>
    </message>
    <portType name="SOAPServer">
        <operation name="testServerreturn">
            <input wsam:Action="http://soapservermaven.mycompany.com/SOAPServer/testServerreturnRequest" message="tns:testServerreturn"/>
            <output wsam:Action="http://soapservermaven.mycompany.com/SOAPServer/testServerreturnResponse" message="tns:testServerreturnResponse"/>
        </operation>
        <operation name="getAllItems">
            <input wsam:Action="http://soapservermaven.mycompany.com/SOAPServer/getAllItemsRequest" message="tns:getAllItems"/>
            <output wsam:Action="http://soapservermaven.mycompany.com/SOAPServer/getAllItemsResponse" message="tns:getAllItemsResponse"/>
        </operation>
    </portType>
    <binding name="SOAPServerPortBinding" type="tns:SOAPServer">
        <soap:binding transport="http://schemas.xmlsoap.org/soap/http" style="document"/>
        <operation name="testServerreturn">
            <soap:operation soapAction=""/>
            <input>
                <soap:body use="literal"/>
            </input>
            <output>
                <soap:body use="literal"/>
            </output>
        </operation>
        <operation name="getAllItems">
            <soap:operation soapAction=""/>
            <input>
                <soap:body use="literal"/>
            </input>
            <output>
                <soap:body use="literal"/>
            </output>
        </operation>
    </binding>
    <service name="mySOAPServer">
        <port name="SOAPServerPort" binding="tns:SOAPServerPortBinding">
            <soap:address location="http://localhost:1234/recipielist"/>
        </port>
    </service>
</definitions>